dwtviz/__init__.py
dwtviz/dwtviz.py
dwtviz-0.0.4.dist-info/DESCRIPTION.rst
dwtviz-0.0.4.dist-info/METADATA
dwtviz-0.0.4.dist-info/RECORD
dwtviz-0.0.4.dist-info/WHEEL
dwtviz-0.0.4.dist-info/metadata.json
dwtviz-0.0.4.dist-info/top_level.txt
