Metadata-Version: 2.0
Name: dwtviz
Version: 0.0.4
Summary: Creates visualizations for discrete wavelet transforms
Home-page: https://github.com/n-s-f/dwtviz
Author: UNKNOWN
Author-email: UNKNOWN
License: UNKNOWN
Platform: UNKNOWN
Requires-Dist: matplotlib
Requires-Dist: pywavelets
